MANIFEST.in
README.rst
requirements-dev.txt
requirements.txt
setup.py
schemabuilder.egg-info/PKG-INFO
schemabuilder.egg-info/SOURCES.txt
schemabuilder.egg-info/dependency_links.txt
schemabuilder.egg-info/requires.txt
schemabuilder.egg-info/top_level.txt
src/schemabuilder/__init__.py
src/schemabuilder/primitives.py
src/schemabuilder/schema.py
src/schemabuilder/utils.py
src/schemabuilder/tests/__init__.py
src/schemabuilder/tests/test_primitives.py
src/schemabuilder/tests/test_schema.py
src/schemabuilder/tests/utils.py