Metadata-Version: 1.1
Name: schemabuilder
Version: 0.2.0
Summary: JSON schema definition helpers
Home-page: https://github.com/dinoboff/schemabuilder
Author: Damien Lebrun
Author-email: dinoboff@gmail.com
License: MIT
Platform: UNKNOWN
Classifier: License :: OSI Approved :: MIT License
Classifier: Development Status :: 1 - Planning
Classifier: Environment :: Web Environment
Classifier: Intended Audience :: Developers
Classifier: Programming Language :: Python :: 2
Classifier: Programming Language :: Python :: 2.7
